fp_convert/__init__.py
fp_convert/__main__.py
fp_convert/colors.py
fp_convert/config.py
fp_convert/errors.py
fp_convert/docs/__init__.py
fp_convert/resources/colordefs.json
fp_convert/utils/__init__.py
fp_convert/utils/builders.py
fp_convert/utils/dbs.py
fp_convert/utils/decorators.py
fp_convert/utils/helpers.py
fp_convert/utils/uml/__init__.py
fp_convert/utils/uml/plantuml.py
fp_convert-0.3.2.dist-info/licenses/LICENSE
fp_convert-0.3.2.dist-info/METADATA
fp_convert-0.3.2.dist-info/WHEEL
fp_convert-0.3.2.dist-info/entry_points.txt
fp_convert-0.3.2.dist-info/top_level.txt
fp_convert-0.3.2.dist-info/RECORD
