Metadata-Version: 2.4
Name: fp-convert
Version: 0.3.2
Summary: A tool to convert Freeplane mindmaps to print-quality PDF documents.
Author-email: K Raghu Prasad <raghuprasad@duck.com>
License-Expression: GPL-3.0-or-later
Project-URL: Homepage, https://github.com/kraghuprasad/fp-convert
Project-URL: Repository, https://github.com/kraghuprasad/fp-convert
Requires-Python: >=3.8
License-File: LICENSE
Requires-Dist: freeplane-io>=0.10.0
Requires-Dist: pylatex>=1.4.2
Requires-Dist: cairosvg>=2.7.1
Requires-Dist: pytz>=2025.1
Requires-Dist: PyYAML>=5.4
Dynamic: license-file
